helga_reminders
